<node id="d329483e-4d51-4a21-b10b-51ba09441f39">
  <container id="58c20bfc-4080-461e-b092-b51f0295161d" name="住院志" description="其书写形式分为住院病历、入院记录、再次或多次入院记录、24小时内入出院记录、24小时内入院死亡记录。" modelCatalogRange="B-10,B-FF" modelDeptRange="" canprint="True" printmodel="入院记录(奉贤)" canbecontinualprint="True" isUploadFolder="False" isNeedSign="False" />
  <container max="10" id="0c1252ad-cdad-445f-93aa-63770a2bbf60" name="24小时入出院或死亡记录" description="包括24小时内入出院记录和入院死亡记录。" modelCatalogRange="B-1090,B-1080" modelDeptRange="" canprint="False" printmodel="入院记录(天津泰达)" canbecontinualprint="True" isUploadFolder="False" isNeedSign="False" />
  <container id="b551c297-a9fd-440a-af87-95c907ad946a" name="首次病程记录" modelCatalogRange="B-42" modelDeptRange="" canprint="True" printmodel="" canbecontinualprint="False" isUploadFolder="False" isNeedSign="False" />
  <container id="dc32a579-3ae8-4f0e-b9bf-74628a81bafe" name="病 程 记 录" modelCatalogRange="B-45,B-48,B-51,B-53,B-56,B-62,B-65,B-73,B-76,B-7655,B-82,B-84,B-88,B-43,B-80,B-52,B-5396" modelDeptRange="" canprint="False" printmodel="default(奉贤)" canbecontinualprint="True" isUploadFolder="False" isNeedSign="False" />
  <container id="95f3559b-32a8-4665-a4d5-d40e2697a06f" name="麻醉记录" description="包括术前与术后" modelCatalogRange="B-98" modelDeptRange="" canprint="False" printmodel="" canbecontinualprint="False" isUploadFolder="False" isNeedSign="False" />
  <container id="0DE98BBB-B4D1-41c5-BAF5-264781324A87" name="与手术相关的记录" description="包括手术记录、术前小结等文件。" modelCatalogRange="B-6260,B-9121,B-91,B-73,B-9110,B-95,B-93,B-94" modelDeptRange="" canprint="False" printmodel="" canbecontinualprint="True" isUploadFolder="False" isNeedSign="False" />
  <container id="07926f6d-71cd-43ed-8832-68c9805b4904" name="会诊单" description="包括病人本次住院期间的主要会诊单。" modelCatalogRange="B-B2" modelDeptRange="" canprint="False" printmodel="" canbecontinualprint="False" isUploadFolder="False" isNeedSign="False" />
  <container id="9a8d7895-d1b7-425b-afbf-b15f78276a96" name="同意书与授权委托书" modelCatalogRange="B-A5,B-E5,B-A532" modelDeptRange="" canprint="True" printmodel="" canbecontinualprint="False" isUploadFolder="False" isNeedSign="False" />
  <container id="42f6b00e-dd01-4a59-911c-f9c17341f420" name="治疗记录单" description="包括各类特殊检查的记录单，如膀胱镜检查记录。" modelCatalogRange="B-E5,B-C2" modelDeptRange="" canprint="False" printmodel="" canbecontinualprint="False" isUploadFolder="False" isNeedSign="False" />
  <container id="8f56e1b1-3e68-4206-8ea9-00d727a1f2ea" name="病例讨论记录" description="专页打印的死亡、疑难、危重病例讨论记录" modelCatalogRange="B-62,B-F2,B-6260,B-9121" modelDeptRange="" canprint="False" printmodel="" canbecontinualprint="False" isUploadFolder="False" isNeedSign="False" />
  <container id="fe191a13-7eca-4d82-b83e-a2ccbf044c31" name="出 院 记 录" modelCatalogRange="B-H1,B-FF,B-H101" modelDeptRange="" canprint="False" printmodel="" canbecontinualprint="False" isUploadFolder="False" isNeedSign="False" />
  <container id="7C0F135B-E379-4c72-AE83-3FE026EE407A" name="病案首页" modelCatalogRange="B-F7" modelDeptRange="" canprint="False" printmodel="" canbecontinualprint="False" isUploadFolder="False" isNeedSign="False" />
  <container id="10810615-a7f8-4f60-aff5-b1df6845ee9f" name="其他" description="适用于管理方面的文档" modelCatalogRange="B-FF,B-E5" modelDeptRange="" canprint="False" printmodel="" canbecontinualprint="False" isUploadFolder="False" isNeedSign="False" />
  <container id="52cd0025-09a2-44df-938a-797bd0194b13" name="高压氧治疗(抢救)记录" description="适用于高压氧治疗" modelCatalogRange="B-53" modelDeptRange="" canprint="True" printmodel="default(岳阳)" canbecontinualprint="True" isUploadFolder="False" isNeedSign="False" />
  <container id="ca21bb4b-c36d-444c-a5a3-6fa002d467d6" name="急诊留观病程记录" description="包括急诊留观相关的病程" modelCatalogRange="B-55" modelDeptRange="" canprint="True" printmodel="" canbecontinualprint="True" isUploadFolder="False" isNeedSign="False" />
  <container id="723ee4bb-f648-4244-91d0-5603cc9ae3dc" name="评价量表" description="对颈椎病等的评价量表" modelCatalogRange="B-E5" modelDeptRange="" canprint="False" printmodel="" canbecontinualprint="False" isUploadFolder="False" isNeedSign="False" />
</node>